questioned/__init__.py
questioned/__main__.py
questioned/app.py
questioned/renderer.py
questioned/utils.py
questioned/questions/__init__.py
questioned/questions/logic_problem.py
questioned/questions/manual_multiple_choice_question.py
questioned/questions/manual_open_question.py
questioned/questions/parsons_problem.py
questioned/questions/question.py
questioned/questions/radix_conversion_question.py
Questioned-0.4.4.dist-info/LICENSE
Questioned-0.4.4.dist-info/METADATA
Questioned-0.4.4.dist-info/WHEEL
Questioned-0.4.4.dist-info/entry_points.txt
Questioned-0.4.4.dist-info/top_level.txt
Questioned-0.4.4.dist-info/RECORD
